wbapi/__init__.py
wbapi-0.0.1.dist-info/METADATA
wbapi-0.0.1.dist-info/WHEEL
wbapi-0.0.1.dist-info/entry_points.txt
wbapi-0.0.1.dist-info/RECORD
